aiohttp_runserver/__init__.py
aiohttp_runserver/livereload.js
aiohttp_runserver/logs.py
aiohttp_runserver/main.py
aiohttp_runserver/serve.py
aiohttp_runserver/watch.py
aiohttp_runserver-0.0.2.dist-info/DESCRIPTION.rst
aiohttp_runserver-0.0.2.dist-info/METADATA
aiohttp_runserver-0.0.2.dist-info/RECORD
aiohttp_runserver-0.0.2.dist-info/WHEEL
aiohttp_runserver-0.0.2.dist-info/entry_points.txt
aiohttp_runserver-0.0.2.dist-info/metadata.json
aiohttp_runserver-0.0.2.dist-info/top_level.txt
aiohttp_runserver-0.0.2.dist-info/zip-safe
